codetypo/__init__.py
codetypo/__main__.py
codetypo/_codetypo.py
codetypo/_spellchecker.py
codetypo/_text_util.py
codetypo/_version.py
codetypo/py.typed
codetypo/data/__init__.py
codetypo/data/dictionary.txt
codetypo/data/dictionary_code.txt
codetypo/data/dictionary_en-GB_to_en-US.txt
codetypo/data/dictionary_informal.txt
codetypo/data/dictionary_names.txt
codetypo/data/dictionary_rare.txt
codetypo/data/dictionary_usage.txt
codetypo/data/linux-kernel.exclude
codetypo/tests/__init__.py
codetypo/tests/test_basic.py
codetypo/tests/test_dictionary.py
codetypo/tests/data/en_GB-additional.wordlist
codetypo/tests/data/en_US-additional.wordlist
requirements/requirements-github-actions.txt
requirements/requirements-tests.txt
requirements/requirements.txt
codetypo-2.3.0.dist-info/COPYING
codetypo-2.3.0.dist-info/METADATA
codetypo-2.3.0.dist-info/WHEEL
codetypo-2.3.0.dist-info/entry_points.txt
codetypo-2.3.0.dist-info/top_level.txt
codetypo-2.3.0.dist-info/RECORD
